{"version": 0.6, "generator": "Overpass API 0.7.62.8 e802775f", "osm3s": {"timestamp_osm_base": "2025-09-19T10:23:03Z", "copyright": "The data included in this document is from www.openstreetmap.org. The data is made available under ODbL."}, "elements": [{"type": "node", "id": 2273085905, "lat": 14.5043638, "lon": -90.9491906, "tags": {"amenity": "college", "name": "Instituto Nacional San Carlos"}}, {"type": "node", "id": 2273085928, "lat": 14.5040747, "lon": -90.9505953}, {"type": "node", "id": 2277281686, "lat": 14.5014651, "lon": -90.9525428, "tags": {"amenity": "kindergarten", "name": "Escuela de P\u00e1rvulos Integral Belice"}}, {"type": "node", "id": 2277281701, "lat": 14.5010688, "lon": -90.9547139, "tags": {"amenity": "townhall", "name": "RENAP"}}, {"type": "node", "id": 4884455029, "lat": 14.4877721, "lon": -90.8043046, "tags": {"amenity": "bank", "name": "Banrural", "name:en": "Banrural", "name:es": "Banrural"}}, {"type": "node", "id": 4978673881, "lat": 14.5255803, "lon": -90.8782747, "tags": {"amenity": "shelter"}}, {"type": "node", "id": 4978673883, "lat": 14.5243963, "lon": -90.8778938, "tags": {"amenity": "shelter"}}, {"type": "node", "id": 4978673888, "lat": 14.5223606, "lon": -90.8782425, "tags": {"amenity": "shelter"}}, {"type": "node", "id": 4978673893, "lat": 14.5191877, "lon": -90.8778992, "tags": {"amenity": "shelter"}}, {"type": "node", "id": 5682153245, "lat": 14.5040379, "lon": -90.9505533}, {"type": "node", "id": 5682153258, "lat": 14.5040566, "lon": -90.9506123}, {"type": "node", "id": 5682153259, "lat": 14.5040823, "lon": -90.9505117}, {"type": "node", "id": 5682153260, "lat": 14.504143, "lon": -90.9505807}, {"type": "node", "id": 5682153261, "lat": 14.5040804, "lon": -90.9506394}, {"type": "node", "id": 6166779585, "lat": 14.514639, "lon": -90.8799572, "tags": {"amenity": "shelter"}}, {"type": "node", "id": 7015713553, "lat": 14.5076072, "lon": -90.8784755, "tags": {"amenity": "shelter"}}, {"type": "node", "id": 9128040539, "lat": 14.5225181, "lon": -90.8029112, "tags": {"alt_name": "Escuela Oficial Urbana Mixta No. 2", "amenity": "school", "name": "Escuela Oficial Urbana Mixta N\u00f9mero 2"}}, {"type": "node", "id": 13040521001, "lat": 14.484387, "lon": -90.804861, "tags": {"addr:city": "San Juan Alotenango", "amenity": "school", "name": "Escuela Oficial Urbana Mixta Mario M\u00e9ndez Montenegro"}}, {"type": "node", "id": 13040521301, "lat": 14.4841685, "lon": -90.8041154, "tags": {"addr:city": "San Juan Alotenango", "addr:state": "Sacatep\u00e9quez", "amenity": "townhall", "name": "Municipalidad de San Juan Alotenango"}}, {"type": "way", "id": 596498829, "nodes": [5682153261, 5682153260, 5682153259, 5682153245, 2273085928, 5682153258, 5682153261], "tags": {"amenity": "school", "building": "yes", "name": "Liceo Cristiano Torre Fuerte"}}]}