{"version": 0.6, "generator": "Overpass API 0.7.62.8 e802775f", "osm3s": {"timestamp_osm_base": "2025-10-16T10:12:27Z", "copyright": "The data included in this document is from www.openstreetmap.org. The data is made available under ODbL."}, "elements": [{"type": "node", "id": 2813165758, "lat": 3.0918729, "lon": 98.4922425, "tags": {"amenity": "fuel", "brand": "Pertamina"}}, {"type": "node", "id": 4410787089, "lat": 3.1479382, "lon": 98.4561991, "tags": {"amenity": "shelter"}}, {"type": "node", "id": 4826957660, "lat": 2.945385, "lon": 98.5203672, "tags": {"amenity": "fuel", "brand": "Pertamina"}}, {"type": "node", "id": 4826957661, "lat": 3.020069, "lon": 98.5393733, "tags": {"amenity": "fuel", "brand": "Pertamina"}}, {"type": "node", "id": 5105421411, "lat": 3.0832015, "lon": 98.5161826, "tags": {"amenity": "fuel", "brand": "Pertamina"}}, {"type": "node", "id": 5346205622, "lat": 3.1054853, "lon": 98.4985474, "tags": {"amenity": "fuel", "name:en": "Pertamina"}}, {"type": "node", "id": 5645206125, "lat": 2.9971942, "lon": 98.5432659, "tags": {"amenity": "fuel"}}, {"type": "node", "id": 7949579881, "lat": 2.9190197, "lon": 98.6304501, "tags": {"amenity": "fuel", "brand": "Pertamina", "fuel:biodiesel": "yes"}}, {"type": "node", "id": 8026875987, "lat": 3.0892491, "lon": 98.4703088, "tags": {"amenity": "fuel", "brand": "Pertamina", "fuel:octane_92": "yes"}}]}